appwashpy/__init__.py
appwashpy/client/__init__.py
appwashpy/client/appwash.py
appwashpy/client/requests.py
appwashpy/common/__init__.py
appwashpy/common/enums.py
appwashpy/common/errors.py
appwashpy/common/helper.py
appwashpy/common/settings.py
appwashpy/core/__init__.py
appwashpy/core/location.py
appwashpy/core/service.py
appwashpy-1.2.5.dist-info/METADATA
appwashpy-1.2.5.dist-info/WHEEL
appwashpy-1.2.5.dist-info/licenses/LICENSE
appwashpy-1.2.5.dist-info/RECORD
