Metadata-Version: 2.1
Name: appwashpy
Version: 1.2.5
Summary: Inofficial API Client for appWash by Miele.
Project-URL: Homepage, https://github.com/fapfaff/appwashpy
Project-URL: Bug Tracker, https://github.com/fapfaff/appwashpy/issues
Author-email: fapfaff <fabian-pfaff@outlook.de>
License: GNU General Public License v3 (GPLv3)
Classifier: License :: OSI Approved :: GNU General Public License v3 (GPLv3)
Classifier: Operating System :: OS Independent
Classifier: Programming Language :: Python :: 3
Requires-Python: >=3.6
Requires-Dist: requests
Provides-Extra: tests
Requires-Dist: black; extra == 'tests'
Requires-Dist: isort; extra == 'tests'
Requires-Dist: pytest; extra == 'tests'
Requires-Dist: pytest-mock; extra == 'tests'
